simple_airbyte/__init__.py
simple_airbyte-0.0.1.dist-info/LICENSE
simple_airbyte-0.0.1.dist-info/METADATA
simple_airbyte-0.0.1.dist-info/WHEEL
simple_airbyte-0.0.1.dist-info/top_level.txt
simple_airbyte-0.0.1.dist-info/RECORD
