Metadata-Version: 2.1
Name: simple-airbyte
Version: 0.0.1
Summary: Airbyte made easy
Author: Unytics
Classifier: Programming Language :: Python :: 3
Classifier: License :: OSI Approved :: MIT License
Classifier: Operating System :: OS Independent
Requires-Python: >=3.6
License-File: LICENSE
